rtt_py-1.3.0.dist-info/METADATA
rtt_py-1.3.0.dist-info/WHEEL
rtt_py-1.3.0.dist-info/entry_points.txt
rtt_py/__init__.py
rtt_py/__main__.py
rtt_py/main.py
rtt_py/services/__init__.py
rtt_py/services/dir_walker.py
rtt_py/services/groq.py
rtt_py/services/url_parser.py
rtt_py/utils/__init__.py
rtt_py/utils/logger.py
rtt_py/utils/util.py
rtt_py-1.3.0.dist-info/RECORD
