Metadata-Version: 2.1
Name: rtt-py
Version: 1.3.0
Summary: Default template for PDM package
Author-Email: Shammi Anand <shammianand101@gmail.com>
License: MIT
Requires-Python: >=3.12
Requires-Dist: typer>=0.15.3
Requires-Dist: structlog>=25.3.0
Requires-Dist: markdownify>=1.1.0
Requires-Dist: requests>=2.32.3
